{
  "documento_numero": "016156684",
  "protocolo": "00240.000044_2025-73",
  "source_file": "17999559.html",
  "model": "fastino/gliner2-large-v1",
  "labels": [
    "pessoa",
    "pessoa_juridica",
    "orgao",
    "cargo",
    "email",
    "cpf",
    "cnpj",
    "matricula",
    "data",
    "valor_monetario",
    "endereco",
    "telefone",
    "numero_processo",
    "lei",
    "decreto",
    "portaria",
    "contrato_edital",
    "assunto",
    "objeto_licitacao",
    "vigencia",
    "url"
  ],
  "entities": {
    "orgao": [
      {
        "text": "SADA-PI"
      },
      {
        "text": "Gabinete Geral"
      }
    ],
    "cargo": [
      {
        "text": "Secretário"
      }
    ]
  },
  "classification": {
    "tipo_documento": "despacho"
  },
  "relations": {},
  "extracted_at": "2026-04-01T10:09:14.011712+00:00"
}