{"nodes": [{"id": "scripts_clean_neo4j_py", "label": "clean_neo4j.py", "file_type": "code", "source_file": "scripts/clean_neo4j.py", "source_location": "L1"}, {"id": "clean_neo4j_clean", "label": "clean()", "file_type": "code", "source_file": "scripts/clean_neo4j.py", "source_location": "L18"}, {"id": "clean_neo4j_main", "label": "main()", "file_type": "code", "source_file": "scripts/clean_neo4j.py", "source_location": "L81"}, {"id": "clean_neo4j_rationale_1", "label": "Clean all data from Neo4j graph database.  Usage:     python scripts/clean_neo4j", "file_type": "rationale", "source_file": "scripts/clean_neo4j.py", "source_location": "L1"}, {"id": "clean_neo4j_rationale_19", "label": "Delete all nodes and relationships in batches, then drop constraints.", "file_type": "rationale", "source_file": "scripts/clean_neo4j.py", "source_location": "L19"}], "edges": [{"source": "scripts_clean_neo4j_py", "target": "argparse", "relation": "imports", "confidence": "EXTRACTED", "source_file": "scripts/clean_neo4j.py", "source_location": "L9", "weight": 1.0}, {"source": "scripts_clean_neo4j_py", "target": "pipeline_cli", "relation": "imports_from", "confidence": "EXTRACTED", "source_file": "scripts/clean_neo4j.py", "source_location": "L11", "weight": 1.0}, {"source": "scripts_clean_neo4j_py", "target": "pipeline_logging_setup", "relation": "imports_from", "confidence": "EXTRACTED", "source_file": "scripts/clean_neo4j.py", "source_location": "L12", "weight": 1.0}, {"source": "scripts_clean_neo4j_py", "target": "pipeline_neo4j_driver", "relation": "imports_from", "confidence": "EXTRACTED", "source_file": "scripts/clean_neo4j.py", "source_location": "L13", "weight": 1.0}, {"source": "scripts_clean_neo4j_py", "target": "clean_neo4j_clean", "relation": "contains", "confidence": "EXTRACTED", "source_file": "scripts/clean_neo4j.py", "source_location": "L18", "weight": 1.0}, {"source": "scripts_clean_neo4j_py", "target": "clean_neo4j_main", "relation": "contains", "confidence": "EXTRACTED", "source_file": "scripts/clean_neo4j.py", "source_location": "L81", "weight": 1.0}, {"source": "clean_neo4j_main", "target": "clean_neo4j_clean", "relation": "calls", "confidence": "EXTRACTED", "source_file": "scripts/clean_neo4j.py", "source_location": "L100", "weight": 1.0}, {"source": "clean_neo4j_rationale_1", "target": "scripts_clean_neo4j_py", "relation": "rationale_for", "confidence": "EXTRACTED", "source_file": "scripts/clean_neo4j.py", "source_location": "L1", "weight": 1.0}, {"source": "clean_neo4j_rationale_19", "target": "clean_neo4j_clean", "relation": "rationale_for", "confidence": "EXTRACTED", "source_file": "scripts/clean_neo4j.py", "source_location": "L19", "weight": 1.0}]}